mpl_colors/__init__.py
mpl_colors/colormaps.py
mpl_colors/generated.py
mpl_colors/mixin.py
mpl_colors-0.2.0.dist-info/LICENSE
mpl_colors-0.2.0.dist-info/METADATA
mpl_colors-0.2.0.dist-info/WHEEL
mpl_colors-0.2.0.dist-info/top_level.txt
mpl_colors-0.2.0.dist-info/RECORD
