Metadata-Version: 2.1
Name: mpl-colors
Version: 0.2.0
Summary: Enums representing named colors available in matplotlib
Home-page: https://github.com/clbarnes/mpl_colors
Author: Chris L. Barnes
Author-email: 
License: MIT
Platform: UNKNOWN
Classifier: Development Status :: 2 - Pre-Alpha
Classifier: License :: OSI Approved :: MIT License
Classifier: Natural Language :: English
Classifier: Programming Language :: Python :: 3.6
Classifier: Programming Language :: Python :: 3.7
Requires-Python: >=3.6
Requires-Dist: colour
Requires-Dist: numpy
Requires-Dist: matplotlib
